deepl_tr_async/__init__.py
deepl_tr_async/__main__.py
deepl_tr_async/deepl_langpair.py
deepl_tr_async/deepl_tr_async.py
deepl_tr_async/detect_lang.py
deepl_tr_async/google_langpair.py
deepl_tr_async/google_tr_async.py
deepl_tr_async/load_env.py
deepl_tr_async-0.0.5.dist-info/entry_points.txt
deepl_tr_async-0.0.5.dist-info/LICENSE
deepl_tr_async-0.0.5.dist-info/WHEEL
deepl_tr_async-0.0.5.dist-info/METADATA
deepl_tr_async-0.0.5.dist-info/RECORD
