Metadata-Version: 2.1
Name: deepl-tr-async
Version: 0.0.5
Summary: deepl translate for free, based on pyppeteer
Home-page: https://github.com/ffreemt/deepl-tr-async
License: MIT
Keywords: mt,language,learning
Author: ffreemt
Requires-Python: >=3.7,<4.0
Classifier: Environment :: Console
Classifier: License :: OSI Approved :: MIT License
Classifier: Operating System :: OS Independent
Classifier: Programming Language :: Python :: 3
Classifier: Programming Language :: Python :: 3.7
Classifier: Programming Language :: Python :: 3.8
Classifier: Topic :: Software Development :: Libraries :: Python Modules
Requires-Dist: absl-py (>=0.9.0,<0.10.0)
Requires-Dist: environs (>=7.3.1,<8.0.0)
Requires-Dist: flake8 (>=3.7.9,<4.0.0)
Requires-Dist: fuzzywuzzy (>=0.18.0,<0.19.0)
Requires-Dist: get-ppbrowser (>=0.1.1,<0.2.0)
Requires-Dist: ipython (>=7.20.0,<8.0.0)
Requires-Dist: linetimer (>=0.1.4,<0.2.0)
Requires-Dist: logzero (>=1.5.0,<2.0.0)
Requires-Dist: polyglot (>=16.7.4,<17.0.0)
Requires-Dist: pycld2 (>=0.41,<0.42)
Requires-Dist: pyicu (>=2.6,<3.0)
Requires-Dist: pyinstaller (>=3.6,<4.0)
Requires-Dist: pyperclip (>=1.7.0,<2.0.0)
Requires-Dist: pyppeteer2 (>=0.2.2,<0.3.0)
Requires-Dist: pyquery (>=1.4.1,<2.0.0)
Requires-Dist: pytest-cov (>=2.8.1,<3.0.0)
Requires-Dist: tqdm (>=4.43.0,<5.0.0)
Project-URL: Repository, https://github.com/ffreemt/deepl-tr-async
